{"cameraMode":{"drawMode":0,"name":"Shaded","section":"Shading Mode"},"sceneLighting":true,"audioPlay":false,"sceneViewState":{"m_AlwaysRefresh":false,"showFog":true,"showSkybox":true,"showFlares":true,"showImageEffects":true,"showParticleSystems":true,"showVisualEffectGraphs":true,"m_FxEnabled":true},"in2DMode":false,"pivot":{"x":6.771793365478516,"y":1.8230323791503907,"z":103.31549835205078},"rotation":{"x":-0.016493435949087144,"y":-0.02006399817764759,"z":0.0004932178417220712,"w":-0.9997777342796326},"size":95.51422119140625,"orthographic":false}